_pyquantile.cp311-win_amd64.pyd
pyquantile/__init__.py
pyquantile/py_quantile_estimator.cpp
pyquantile/quantile-estimator.cpp
pyquantile/quantile-estimator.h
pyquantile-0.2.2.dist-info/licenses/LICENSE
pyquantile-0.2.2.dist-info/METADATA
pyquantile-0.2.2.dist-info/WHEEL
pyquantile-0.2.2.dist-info/top_level.txt
pyquantile-0.2.2.dist-info/RECORD
