Metadata-Version: 2.4
Name: pyquantile
Version: 0.2.2
Summary: A fast quantile estimator for streamed data. Produces a quantile estimate without storing any data points.
Author: Richard Smythe
License-Expression: MIT
Requires-Python: >=3.8
License-File: LICENSE
Requires-Dist: numpy
Requires-Dist: pybind11
Dynamic: license-file
Dynamic: requires-python
